opentargets_ontologyutils/__init__.py
opentargets_ontologyutils/eco_so.py
opentargets_ontologyutils/efo.py
opentargets_ontologyutils/hpo.py
opentargets_ontologyutils/mp.py
opentargets_ontologyutils/rdf_utils.py
opentargets_ontologyutils/version.py
opentargets_ontologyutils-1.2.4.dist-info/LICENSE
opentargets_ontologyutils-1.2.4.dist-info/METADATA
opentargets_ontologyutils-1.2.4.dist-info/WHEEL
opentargets_ontologyutils-1.2.4.dist-info/top_level.txt
opentargets_ontologyutils-1.2.4.dist-info/RECORD
