Metadata-Version: 2.1
Name: opentargets-ontologyutils
Version: 1.2.4
Summary: Ontology utilities at targetvalidation.org
Home-page: https://github.com/opentargets/ontology-utils
Author: OpenTargets Core Team <support@targetvalidation.org>
Author-email: support@targetvalidation.org
License: Apache License, Version 2.0
Download-URL: https://github.com/opentargets/ontology-utils/archive/1.2.4.tar.gz
Keywords: opentargets,bioinformatics,ontology
Platform: any
Classifier: License :: OSI Approved :: Apache Software License
Classifier: Programming Language :: Python :: 2
Classifier: Programming Language :: Python :: 3
Provides-Extra: dev
